cu_automata_3d/__init__.py
cu_automata_3d/src/ApplyFuncConstructor.py
cu_automata_3d/src/Environment.py
cu_automata_3d/src/GrowthFuncConstructor.py
cu_automata_3d/src/InitStateConstructor.py
cu_automata_3d/src/KernelConstructor.py
cu_automata_3d/src/KernelFunctions.py
cu_automata_3d/src/PremadeAutomata.py
cu_automata_3d/src/Visualizer.py
cu_automata_3d/src/__init__.py
cu_automata_3d-1.0.0.dist-info/LICENSE
cu_automata_3d-1.0.0.dist-info/METADATA
cu_automata_3d-1.0.0.dist-info/WHEEL
cu_automata_3d-1.0.0.dist-info/top_level.txt
cu_automata_3d-1.0.0.dist-info/RECORD
